gytoolkit/__init__.py
gytoolkit/analyzer/__init__.py
gytoolkit/analyzer/constants.py
gytoolkit/analyzer/indicator.py
gytoolkit/analyzer/objects.py
gytoolkit/analyzer/utils.py
gytoolkit/broker.py
gytoolkit/client.py
gytoolkit/constants.py
gytoolkit/datamanager/__init__.py
gytoolkit/datamanager/benchmark.py
gytoolkit/datamanager/constants.py
gytoolkit/datamanager/dataloader.py
gytoolkit/datamanager/fundevent.py
gytoolkit/datamanager/net_value.py
gytoolkit/datamanager/prodinfo.py
gytoolkit/datamanager/trade.py
gytoolkit/datamanager/utils.py
gytoolkit/mailparser/__init__.py
gytoolkit/mailparser/constants.py
gytoolkit/mailparser/mailparser.py
gytoolkit/mailparser/utils.py
gytoolkit/manager.py
gytoolkit/position.py
gytoolkit/ppwdbapi/__init__.py
gytoolkit/ppwdbapi/api.py
gytoolkit/ppwdbapi/client.py
gytoolkit/ppwdbapi/constants.py
gytoolkit/ppwdbapi/tables.py
gytoolkit/ppwdbapi/utils.py
gytoolkit/product.py
gytoolkit/utils.py
gytoolkit-1.4.3.dist-info/LICENSE
gytoolkit-1.4.3.dist-info/METADATA
gytoolkit-1.4.3.dist-info/WHEEL
gytoolkit-1.4.3.dist-info/RECORD
